<?xml version="1.0" encoding="utf-8"?>

<STHS-TodayGame>
<Information>STHS Today Game Version 2</Information>
<Date>August 17, 2025 at 11:41</Date>
<Game><GameNumber>Farm18</GameNumber><Link>UHA-Farm-18.html</Link><VisitorTeam>Laval Rocket</VisitorTeam><VisitorTeamScore>1</VisitorTeamScore><VisitorTeamGoal>Unknown Player(1)</VisitorTeamGoal><VisitorTeamGoaler>Jakub Dobes (LAV), 15 saves from 19 shots - (0.789), L, 1-1-0, 60:00 minutes </VisitorTeamGoaler><HomeTeam>Calgary Wranglers</HomeTeam><HomeTeamScore>4</HomeTeamScore><HomeTeamGoal>Sam Morton(1,2,3), Adam Klapka(1)</HomeTeamGoal><HomeTeamGoaler>Unknown Goalie (CGY), 6 saves from 7 shots - (0.857), W, 1-0-0, 60:00 minutes </HomeTeamGoaler></Game>
<Game><GameNumber>Farm19</GameNumber><Link>UHA-Farm-19.html</Link><VisitorTeam>Rockford IceHogs</VisitorTeam><VisitorTeamScore>3</VisitorTeamScore><VisitorTeamGoal>Unknown Player(1), Colton Dach(2), Nolan Allan(1)</VisitorTeamGoal><VisitorTeamGoaler>Unknown Goalie (RCK), 16 saves from 19 shots - (0.842), OTL, 0-0-1, 65:00 minutes </VisitorTeamGoaler><HomeTeam>Belleville Senators</HomeTeam><HomeTeamScore>4</HomeTeamScore><HomeTeamGoal>Unknown Player(1,2), Zack MacEwen(1)</HomeTeamGoal><HomeTeamGoaler>Mads Sogaard (BVL), 8 saves from 11 shots - (0.727), W, 1-0-0, 65:00 minutes </HomeTeamGoaler></Game>
<Game><GameNumber>Farm20</GameNumber><Link>UHA-Farm-20.html</Link><VisitorTeam>Utica Comets</VisitorTeam><VisitorTeamScore>1</VisitorTeamScore><VisitorTeamGoal>Unknown Player(1)</VisitorTeamGoal><VisitorTeamGoaler>Nico Daws (UTI), 14 saves from 18 shots - (0.778), L, 2-1-0, 41:47 minutes Unknown Goalie (UTI), 8 saves from 12 shots - (0.667), 18:13 minutes </VisitorTeamGoaler><HomeTeam>Cleveland Monsters</HomeTeam><HomeTeamScore>8</HomeTeamScore><HomeTeamGoal>Mikael Pyyhtia(1), Kevin Labanc(1,2), Denton Mateychuk(1,2), Luca Del Bel Belluz(1,2,3)</HomeTeamGoal><HomeTeamGoaler>Jet Greaves (CLV), 12 saves from 13 shots - (0.923), W, 1-0-0, 60:00 minutes </HomeTeamGoaler></Game>
<Game><GameNumber>Farm21</GameNumber><Link>UHA-Farm-21.html</Link><VisitorTeam>San Jose Barracuda</VisitorTeam><VisitorTeamScore>7</VisitorTeamScore><VisitorTeamGoal>Cam Lund(1), Unknown Player(1,2), Patrick Giles(1), Jack Thompson(2), Carl Grundstrom(3,4)</VisitorTeamGoal><VisitorTeamGoaler>Unknown Goalie (SJB), 11 saves from 14 shots - (0.786), W, 1-0-0, 60:00 minutes </VisitorTeamGoaler><HomeTeam>Texas Stars</HomeTeam><HomeTeamScore>3</HomeTeamScore><HomeTeamGoal>Unknown Player(1), Colin Blackwell(1), Lian Bichsel(1)</HomeTeamGoal><HomeTeamGoaler>Unknown Goalie (TEX), 19 saves from 24 shots - (0.792), L, 0-1-0, 45:03 minutes Unknown Goalie (TEX), 3 saves from 5 shots - (0.600), 14:57 minutes </HomeTeamGoaler></Game>
<Game><GameNumber>Pro22</GameNumber><Link>UHA-22.html</Link><VisitorTeam>Los Angeles Kings</VisitorTeam><VisitorTeamScore>4</VisitorTeamScore><VisitorTeamGoal>Adrian Kempe(4), Kevin Fiala(3,4,5)</VisitorTeamGoal><VisitorTeamGoaler>Darcy Kuemper (LAK), 16 saves from 21 shots - (0.762), L, 1-1-1, 45:39 minutes David Rittich (LAK), 10 saves from 12 shots - (0.833), 14:21 minutes </VisitorTeamGoaler><HomeTeam>Winnipeg Jets</HomeTeam><HomeTeamScore>7</HomeTeamScore><HomeTeamGoal>Adam Lowry(1), Gabriel Vilardi(1,2,3), Kyle Connor(1,2), Neal Pionk(1)</HomeTeamGoal><HomeTeamGoaler>Connor Hellebuyck (WPG), 26 saves from 30 shots - (0.867), W, 1-1-0, 60:00 minutes </HomeTeamGoaler></Game>
<Game><GameNumber>Farm22</GameNumber><Link>UHA-Farm-22.html</Link><VisitorTeam>Syracuse Crunch</VisitorTeam><VisitorTeamScore>3</VisitorTeamScore><VisitorTeamGoal>Conor Geekie(8), Nick Perbix(7,8)</VisitorTeamGoal><VisitorTeamGoaler>Unknown Goalie (SYR), 13 saves from 15 shots - (0.867), W, 1-0-0, 60:00 minutes </VisitorTeamGoaler><HomeTeam>Jacksonville Barons</HomeTeam><HomeTeamScore>2</HomeTeamScore><HomeTeamGoal>Jonah Gadjovich(4), Unknown Player(1)</HomeTeamGoal><HomeTeamGoaler>Unknown Goalie (JAK), 16 saves from 19 shots - (0.842), L, 0-1-0, 59:34 minutes </HomeTeamGoaler></Game>
<Game><GameNumber>Pro23</GameNumber><Link>UHA-23.html</Link><VisitorTeam>St. Louis Blues</VisitorTeam><VisitorTeamScore>3</VisitorTeamScore><VisitorTeamGoal>Jake Neighbours(1), Mathieu Joseph(1), Robert Thomas(1)</VisitorTeamGoal><VisitorTeamGoaler>Jordan Binnington (STL), 29 saves from 34 shots - (0.853), L, 0-2-0, 60:00 minutes </VisitorTeamGoaler><HomeTeam>Calgary Flames</HomeTeam><HomeTeamScore>5</HomeTeamScore><HomeTeamGoal>Anthony Mantha(2), Daniil Miromanov(1), Jonathan Huberdeau(1), MacKenzie Weegar(1), Nazem Kadri(2)</HomeTeamGoal><HomeTeamGoaler>Dustin Wolf (CGY), 25 saves from 28 shots - (0.893), W, 1-2-0, 60:00 minutes </HomeTeamGoaler></Game>
<Game><GameNumber>Farm23</GameNumber><Link>UHA-Farm-23.html</Link><VisitorTeam>Iowa Wild</VisitorTeam><VisitorTeamScore>5</VisitorTeamScore><VisitorTeamGoal>Devin Shore(7,8,9), David Jiricek(5,6)</VisitorTeamGoal><VisitorTeamGoaler>Unknown Goalie (IOW), 9 saves from 11 shots - (0.818), W, 1-0-0, 60:00 minutes </VisitorTeamGoaler><HomeTeam>Milwaukee Admirals</HomeTeam><HomeTeamScore>2</HomeTeamScore><HomeTeamGoal>Kieffer Bellows(2,3)</HomeTeamGoal><HomeTeamGoaler>Unknown Goalie (MIL), 19 saves from 24 shots - (0.792), L, 0-1-0, 60:00 minutes </HomeTeamGoaler></Game>
<Game><GameNumber>Pro24</GameNumber><Link>UHA-24.html</Link><VisitorTeam>Buffalo Sabres</VisitorTeam><VisitorTeamScore>5</VisitorTeamScore><VisitorTeamGoal>JJ Peterka(2), Josh Norris(1,2), Rasmus Dahlin(3), Tage Thompson(4)</VisitorTeamGoal><VisitorTeamGoaler>Ukko-Pekka Luukkonen (BUF), 25 saves from 26 shots - (0.962), W, 2-0-0, 60:00 minutes </VisitorTeamGoaler><HomeTeam>Boston Bruins</HomeTeam><HomeTeamScore>1</HomeTeamScore><HomeTeamGoal>Casey Mittelstadt(1)</HomeTeamGoal><HomeTeamGoaler>Jeremy Swayman (BOS), 13 saves from 17 shots - (0.765), L, 1-2-0, 34:18 minutes Joonas Korpisalo (BOS), 10 saves from 11 shots - (0.909), 25:42 minutes </HomeTeamGoaler></Game>
<Game><GameNumber>Farm24</GameNumber><Link>UHA-Farm-24.html</Link><VisitorTeam>Cleveland Monsters</VisitorTeam><VisitorTeamScore>1</VisitorTeamScore><VisitorTeamGoal>Denton Mateychuk(3)</VisitorTeamGoal><VisitorTeamGoaler>Jet Greaves (CLV), 19 saves from 21 shots - (0.905), L, 1-1-0, 59:42 minutes </VisitorTeamGoaler><HomeTeam>Rochester Americans</HomeTeam><HomeTeamScore>2</HomeTeamScore><HomeTeamGoal>Unknown Player(1), Peyton Krebs(1)</HomeTeamGoal><HomeTeamGoaler>Devon Levi (ROC), 20 saves from 21 shots - (0.952), W, 1-1-0, 60:00 minutes </HomeTeamGoaler></Game>
<Game><GameNumber>Pro25</GameNumber><Link>UHA-25.html</Link><VisitorTeam>Toronto Maple Leafs</VisitorTeam><VisitorTeamScore>4</VisitorTeamScore><VisitorTeamGoal>Mitch Marner(1), Oliver Ekman-Larsson(1), William Nylander(2,3)</VisitorTeamGoal><VisitorTeamGoaler>Anthony Stolarz (TOR), 26 saves from 29 shots - (0.897), W, 2-0-0, 60:00 minutes </VisitorTeamGoaler><HomeTeam>Detroit Red Wings</HomeTeam><HomeTeamScore>3</HomeTeamScore><HomeTeamGoal>Alex DeBrincat(2,3), Patrick Kane(1)</HomeTeamGoal><HomeTeamGoaler>Cam Talbot (DET), 31 saves from 35 shots - (0.886), L, 1-1-0, 59:00 minutes </HomeTeamGoaler></Game>
<Game><GameNumber>Farm25</GameNumber><Link>UHA-Farm-25.html</Link><VisitorTeam>Calgary Wranglers</VisitorTeam><VisitorTeamScore>5</VisitorTeamScore><VisitorTeamGoal>Sam Morton(4), Adam Klapka(2), Justin Kirkland(1), Ryan Lomberg(1)</VisitorTeamGoal><VisitorTeamGoaler>Unknown Goalie (CGY), 16 saves from 20 shots - (0.800), W, 1-0-0, 64:34 minutes </VisitorTeamGoaler><HomeTeam>Bakersfield Condors</HomeTeam><HomeTeamScore>4</HomeTeamScore><HomeTeamGoal>Vasily Podkolzin(1), Unknown Player(1,2), Max Jones(1)</HomeTeamGoal><HomeTeamGoaler>Unknown Goalie (BAK), 15 saves from 19 shots - (0.789), OTL, 0-0-1, 65:00 minutes </HomeTeamGoaler></Game>
<Game><GameNumber>Pro26</GameNumber><Link>UHA-26.html</Link><VisitorTeam>New Jersey Devils</VisitorTeam><VisitorTeamScore>3</VisitorTeamScore><VisitorTeamGoal>Nico Hischier(1,2), Stefan Noesen(1)</VisitorTeamGoal><VisitorTeamGoaler>Jacob Markstrom (NJD), 12 saves from 16 shots - (0.750), L, 1-1-0, 23:22 minutes Jake Allen (NJD), 14 saves from 17 shots - (0.824), 36:38 minutes </VisitorTeamGoaler><HomeTeam>Tampa Bay Lightning</HomeTeam><HomeTeamScore>7</HomeTeamScore><HomeTeamGoal>Brandon Hagel(1,2), Brayden Point(3), Jake Guentzel(2,3), Nikita Kucherov(2,3)</HomeTeamGoal><HomeTeamGoaler>Andrei Vasilevskiy (TBL), 25 saves from 28 shots - (0.893), W, 2-0-0, 60:00 minutes </HomeTeamGoaler></Game>
<Game><GameNumber>Pro27</GameNumber><Link>UHA-27.html</Link><VisitorTeam>Ottawa Senators</VisitorTeam><VisitorTeamScore>4</VisitorTeamScore><VisitorTeamGoal>Drake Batherson(1), Fabian Zetterlund(1), Shane Pinto(1), Thomas Chabot(1)</VisitorTeamGoal><VisitorTeamGoaler>Linus Ullmark (OTT), 22 saves from 27 shots - (0.815), L, 0-1-1, 60:00 minutes </VisitorTeamGoaler><HomeTeam>Florida Panthers</HomeTeam><HomeTeamScore>5</HomeTeamScore><HomeTeamGoal>Carter Verhaeghe(3), Sam Reinhart(4,5,6,7)</HomeTeamGoal><HomeTeamGoaler>Sergei Bobrovsky (FLA), 28 saves from 32 shots - (0.875), W, 2-1-0, 60:00 minutes </HomeTeamGoaler></Game>
<Game><GameNumber>Pro28</GameNumber><Link>UHA-28.html</Link><VisitorTeam>Washington Capitals</VisitorTeam><VisitorTeamScore>2</VisitorTeamScore><VisitorTeamGoal>Alex Ovechkin(1,2)</VisitorTeamGoal><VisitorTeamGoaler>Logan Thompson (WSH), 33 saves from 36 shots - (0.917), L, 1-1-0, 59:01 minutes </VisitorTeamGoaler><HomeTeam>New York Islanders</HomeTeam><HomeTeamScore>3</HomeTeamScore><HomeTeamGoal>Anders Lee(2), Bo Horvat(1,2)</HomeTeamGoal><HomeTeamGoaler>Ilya Sorokin (NYI), 33 saves from 35 shots - (0.943), W, 1-1-0, 60:00 minutes </HomeTeamGoaler></Game>
<Game><GameNumber>Pro29</GameNumber><Link>UHA-29.html</Link><VisitorTeam>New York Rangers</VisitorTeam><VisitorTeamScore>5</VisitorTeamScore><VisitorTeamGoal>Adam Fox(2), Artemi Panarin(3,4,5), Chris Kreider(3)</VisitorTeamGoal><VisitorTeamGoaler>Igor Shesterkin (NYR), 32 saves from 35 shots - (0.914), W, 2-1-0, 60:00 minutes </VisitorTeamGoaler><HomeTeam>Pittsburgh Penguins</HomeTeam><HomeTeamScore>3</HomeTeamScore><HomeTeamGoal>Bryan Rust(3), Erik Karlsson(1), Sidney Crosby(1)</HomeTeamGoal><HomeTeamGoaler>Alex Nedeljkovic (PIT), 26 saves from 31 shots - (0.839), L, 1-2-0, 60:00 minutes </HomeTeamGoaler></Game>
<Game><GameNumber>Pro30</GameNumber><Link>UHA-30.html</Link><VisitorTeam>Philadelphia Flyers</VisitorTeam><VisitorTeamScore>1</VisitorTeamScore><VisitorTeamGoal>Owen Tippett(2)</VisitorTeamGoal><VisitorTeamGoaler>Ivan Fedotov (PHI), 6 saves from 9 shots - (0.667), 26:57 minutes Samuel Ersson (PHI), 13 saves from 17 shots - (0.765), L, 1-1-0, 33:03 minutes </VisitorTeamGoaler><HomeTeam>Carolina Hurricanes</HomeTeam><HomeTeamScore>7</HomeTeamScore><HomeTeamGoal>Andrei Svechnikov(1,2,3), Jack Roslovic(1), Jordan Martinook(1), Seth Jarvis(2,3)</HomeTeamGoal><HomeTeamGoaler>Pyotr Kochetkov (CAR), 22 saves from 23 shots - (0.957), W, 1-1-0, 60:00 minutes </HomeTeamGoaler></Game>
<Game><GameNumber>Pro31</GameNumber><Link>UHA-31.html</Link><VisitorTeam>Montreal Canadiens</VisitorTeam><VisitorTeamScore>3</VisitorTeamScore><VisitorTeamGoal>Christian Dvorak(1), Nick Suzuki(1,2)</VisitorTeamGoal><VisitorTeamGoaler>Sam Montembeault (MTL), 28 saves from 30 shots - (0.933), W, 1-2-0, 59:50 minutes </VisitorTeamGoaler><HomeTeam>Chicago Blackhawks</HomeTeam><HomeTeamScore>2</HomeTeamScore><HomeTeamGoal>Alec Martinez(1), Jason Dickinson(1)</HomeTeamGoal><HomeTeamGoaler>Arvid Soderblom (CHI), 21 saves from 24 shots - (0.875), OTL, 0-1-2, 60:18 minutes </HomeTeamGoaler></Game>
<Game><GameNumber>Pro32</GameNumber><Link>UHA-32.html</Link><VisitorTeam>Utah Mammoth</VisitorTeam><VisitorTeamScore>4</VisitorTeamScore><VisitorTeamGoal>Clayton Keller(1), Dylan Guenther(1), Lawson Crouse(1), Matias Maccelli(1)</VisitorTeamGoal><VisitorTeamGoaler>Karel Vejmelka (UTA), 27 saves from 30 shots - (0.900), W, 1-1-0, 60:00 minutes </VisitorTeamGoaler><HomeTeam>Nashville Predators</HomeTeam><HomeTeamScore>3</HomeTeamScore><HomeTeamGoal>Brady Skjei(1), Filip Forsberg(2), Steven Stamkos(2)</HomeTeamGoal><HomeTeamGoaler>Juuse Saros (NSH), 29 saves from 33 shots - (0.879), L, 1-1-0, 60:00 minutes </HomeTeamGoaler></Game>
<Game><GameNumber>Pro33</GameNumber><Link>UHA-33.html</Link><VisitorTeam>Columbus Blue Jackets</VisitorTeam><VisitorTeamScore>5</VisitorTeamScore><VisitorTeamGoal>Cole Sillinger(1), Dmitri Voronkov(1), Sean Monahan(1), Zach Werenski(1,2)</VisitorTeamGoal><VisitorTeamGoaler>Elvis Merzlikins (CBJ), 31 saves from 33 shots - (0.939), W, 1-1-0, 60:00 minutes </VisitorTeamGoaler><HomeTeam>Minnesota Wild</HomeTeam><HomeTeamScore>2</HomeTeamScore><HomeTeamGoal>Joel Eriksson Ek(1), Marcus Foligno(1)</HomeTeamGoal><HomeTeamGoaler>Filip Gustavsson (MIN), 25 saves from 30 shots - (0.833), L, 1-1-0, 60:00 minutes </HomeTeamGoaler></Game>
<Game><GameNumber>Pro34</GameNumber><Link>UHA-34.html</Link><VisitorTeam>Dallas Stars</VisitorTeam><VisitorTeamScore>5</VisitorTeamScore><VisitorTeamGoal>Jamie Benn(1), Matt Duchene(1), Mikko Rantanen(1,2), Wyatt Johnston(1)</VisitorTeamGoal><VisitorTeamGoaler>Jake Oettinger (DAL), 39 saves from 43 shots - (0.907), W, 2-0-0, 60:12 minutes </VisitorTeamGoaler><HomeTeam>Colorado Avalanche</HomeTeam><HomeTeamScore>4</HomeTeamScore><HomeTeamGoal>Cale Makar(4), Devon Toews(2), Jonathan Drouin(1), Nathan MacKinnon(2)</HomeTeamGoal><HomeTeamGoaler>Mackenzie Blackwood (COL), 23 saves from 28 shots - (0.821), OTL, 1-1-1, 60:12 minutes </HomeTeamGoaler></Game>
<Game><GameNumber>Pro35</GameNumber><Link>UHA-35.html</Link><VisitorTeam>Vancouver Canucks</VisitorTeam><VisitorTeamScore>5</VisitorTeamScore><VisitorTeamGoal>Filip Chytil(1), Jake DeBrusk(1), Quinn Hughes(1,2,3)</VisitorTeamGoal><VisitorTeamGoaler>Thatcher Demko (VAN), 25 saves from 31 shots - (0.806), L, 1-1-0, 59:10 minutes </VisitorTeamGoaler><HomeTeam>Edmonton Oilers</HomeTeam><HomeTeamScore>6</HomeTeamScore><HomeTeamGoal>Adam Henrique(1), Evan Bouchard(1), Leon Draisaitl(2,3), Mattias Ekholm(1,2)</HomeTeamGoal><HomeTeamGoaler>Stuart Skinner (EDM), 28 saves from 33 shots - (0.848), W, 2-0-0, 60:00 minutes </HomeTeamGoaler></Game>
<Game><GameNumber>Pro36</GameNumber><Link>UHA-36.html</Link><VisitorTeam>Anaheim Ducks</VisitorTeam><VisitorTeamScore>3</VisitorTeamScore><VisitorTeamGoal>Mason McTavish(1,2), Troy Terry(1)</VisitorTeamGoal><VisitorTeamGoaler>Lukas Dostal (ANA), 24 saves from 25 shots - (0.960), W, 1-1-0, 60:00 minutes </VisitorTeamGoaler><HomeTeam>San Jose Sharks</HomeTeam><HomeTeamScore>1</HomeTeamScore><HomeTeamGoal>Macklin Celebrini(2)</HomeTeamGoal><HomeTeamGoaler>Alexandar Georgiev (SJS), 22 saves from 25 shots - (0.880), L, 1-1-0, 60:00 minutes </HomeTeamGoaler></Game>
<Game><GameNumber>Pro37</GameNumber><Link>UHA-37.html</Link><VisitorTeam>Vegas Golden Knights</VisitorTeam><VisitorTeamScore>8</VisitorTeamScore><VisitorTeamGoal>Brandon Saad(1), Reilly Smith(1,2,3), Tomas Hertl(2), William Karlsson(1,2,3)</VisitorTeamGoal><VisitorTeamGoaler>Adin Hill (VGK), 23 saves from 27 shots - (0.852), W, 2-1-0, 60:00 minutes </VisitorTeamGoaler><HomeTeam>Seattle Kraken</HomeTeam><HomeTeamScore>4</HomeTeamScore><HomeTeamGoal>Brandon Montour(1,2), Jared McCann(1,2)</HomeTeamGoal><HomeTeamGoaler>Joey Daccord (SEA), 15 saves from 19 shots - (0.789), 34:11 minutes Philipp Grubauer (SEA), 13 saves from 17 shots - (0.765), L, 0-1-0, 25:49 minutes </HomeTeamGoaler></Game>
<Game><GameNumber>Farm26</GameNumber><Link>UHA-Farm-26.html</Link><VisitorTeam>Wilkes-Barre/Scranton Penguins</VisitorTeam><VisitorTeamScore>3</VisitorTeamScore><VisitorTeamGoal>Valtteri Puustinen(3), Vladislav Kolyachonok(2), Rutger McGroarty(1)</VisitorTeamGoal><VisitorTeamGoaler>Joel Blomqvist (WSP), 13 saves from 15 shots - (0.867), W, 1-0-0, 59:23 minutes </VisitorTeamGoaler><HomeTeam>Lehigh Valley Phantoms</HomeTeam><HomeTeamScore>2</HomeTeamScore><HomeTeamGoal>Jakob Pelletier(9,10)</HomeTeamGoal><HomeTeamGoaler>Aleksei Kolosov (LVP), 19 saves from 22 shots - (0.864), OTL, 1-0-1, 60:08 minutes </HomeTeamGoaler></Game>
<Game><GameNumber>Farm27</GameNumber><Link>UHA-Farm-27.html</Link><VisitorTeam>Bridgeport Islanders</VisitorTeam><VisitorTeamScore>1</VisitorTeamScore><VisitorTeamGoal>Scott Perunovich(2)</VisitorTeamGoal><VisitorTeamGoaler>Marcus Hogberg (BRI), 22 saves from 26 shots - (0.846), L, 1-1-0, 60:00 minutes </VisitorTeamGoaler><HomeTeam>Abbotsford Canucks</HomeTeam><HomeTeamScore>4</HomeTeamScore><HomeTeamGoal>Aatu Raty(3,4,5), Nils Aman(1)</HomeTeamGoal><HomeTeamGoaler>Nikita Tolopilo (ABB), 9 saves from 10 shots - (0.900), W, 1-0-1, 60:00 minutes </HomeTeamGoaler></Game>
<Game><GameNumber>Farm28</GameNumber><Link>UHA-Farm-28.html</Link><VisitorTeam>Ontario Reign</VisitorTeam><VisitorTeamScore>3</VisitorTeamScore><VisitorTeamGoal>Samuel Helenius(1), Akil Thomas(3,4)</VisitorTeamGoal><VisitorTeamGoaler>Erik Portillo (ONT), 17 saves from 19 shots - (0.895), W, 2-0-0, 60:00 minutes </VisitorTeamGoaler><HomeTeam>Springfield Thunderbirds</HomeTeam><HomeTeamScore>2</HomeTeamScore><HomeTeamGoal>Unknown Player(1), Nathan Walker(5)</HomeTeamGoal><HomeTeamGoaler>Unknown Goalie (SPR), 14 saves from 17 shots - (0.824), L, 0-1-0, 59:00 minutes </HomeTeamGoaler></Game>
<Game><GameNumber>Farm29</GameNumber><Link>UHA-Farm-29.html</Link><VisitorTeam>Hartford Wolf Pack</VisitorTeam><VisitorTeamScore>2</VisitorTeamScore><VisitorTeamGoal>Zac Jones(5), Matt Rempe(7)</VisitorTeamGoal><VisitorTeamGoaler>Louis Domingue (HFD), 12 saves from 16 shots - (0.750), L, 1-1-0, 32:21 minutes Unknown Goalie (HFD), 1 saves from 3 shots - (0.333), 27:39 minutes </VisitorTeamGoaler><HomeTeam>Henderson Silver Knights</HomeTeam><HomeTeamScore>6</HomeTeamScore><HomeTeamGoal>Callahan Burke(6), Victor Olofsson(3,4), Alexander Holtz(8,9), Tanner Laczynski(11)</HomeTeamGoal><HomeTeamGoaler>Akira Schmid (HSK), 13 saves from 15 shots - (0.867), W, 2-1-0, 60:00 minutes </HomeTeamGoaler></Game>
<Game><GameNumber>Farm30</GameNumber><Link>UHA-Farm-30.html</Link><VisitorTeam>Colorado Eagles</VisitorTeam><VisitorTeamScore>6</VisitorTeamScore><VisitorTeamGoal>Jimmy Vesey(2,3), Sam Malinski(4), Ivan Ivan(1,2), Jack Drury(3)</VisitorTeamGoal><VisitorTeamGoaler>Unknown Goalie (COL), 16 saves from 19 shots - (0.842), W, 1-0-0, 60:00 minutes </VisitorTeamGoaler><HomeTeam>Iowa Wild</HomeTeam><HomeTeamScore>3</HomeTeamScore><HomeTeamGoal>Devin Shore(10), Unknown Player(1,2)</HomeTeamGoal><HomeTeamGoaler>Unknown Goalie (IOW), 13 saves from 17 shots - (0.765), L, 0-1-0, 43:31 minutes Unknown Goalie (IOW), 2 saves from 4 shots - (0.500), 16:29 minutes </HomeTeamGoaler></Game>
<Game><GameNumber>Farm31</GameNumber><Link>UHA-Farm-31.html</Link><VisitorTeam>Charlotte Checkers</VisitorTeam><VisitorTeamScore>5</VisitorTeamScore><VisitorTeamGoal>Tyson Jost(3), Unknown Player(1,2), Justin Robidas(1), Ty Smith(5)</VisitorTeamGoal><VisitorTeamGoaler>Spencer Martin (CHA), 20 saves from 23 shots - (0.870), W, 2-1-0, 60:00 minutes </VisitorTeamGoaler><HomeTeam>Utica Comets</HomeTeam><HomeTeamScore>3</HomeTeamScore><HomeTeamGoal>Nathan Bastian(3), Seamus Casey(11,12)</HomeTeamGoal><HomeTeamGoaler>Nico Daws (UTI), 24 saves from 29 shots - (0.828), L, 2-2-0, 60:00 minutes </HomeTeamGoaler></Game>
<Game><GameNumber>Farm32</GameNumber><Link>UHA-Farm-32.html</Link><VisitorTeam>Laval Rocket</VisitorTeam><VisitorTeamScore>2</VisitorTeamScore><VisitorTeamGoal>Lucas Condotta(2), Logan Mailloux(5)</VisitorTeamGoal><VisitorTeamGoaler>Jakub Dobes (LAV), 18 saves from 21 shots - (0.857), L, 1-2-0, 60:00 minutes </VisitorTeamGoaler><HomeTeam>Toronto Marlies</HomeTeam><HomeTeamScore>3</HomeTeamScore><HomeTeamGoal>Unknown Player(1), Alex Steeves(1), Philippe Myers(1)</HomeTeamGoal><HomeTeamGoaler>Dennis Hildeby (TOR), 10 saves from 12 shots - (0.833), W, 1-1-0, 60:00 minutes </HomeTeamGoaler></Game>
<Game><GameNumber>Farm33</GameNumber><Link>UHA-Farm-33.html</Link><VisitorTeam>Grand Rapids Griffins</VisitorTeam><VisitorTeamScore>1</VisitorTeamScore><VisitorTeamGoal></VisitorTeamGoal><VisitorTeamGoaler>Alex Lyon (GRG), 8 saves from 8 shots - (1.000), W, 3-0-0, 65:00 minutes </VisitorTeamGoaler><HomeTeam>Coachella Valley Firebirds</HomeTeam><HomeTeamScore>0</HomeTeamScore><HomeTeamGoal></HomeTeamGoal><HomeTeamGoaler>Unknown Goalie (CVF), 20 saves from 20 shots - (1.000), OTL, 0-0-1, 65:00 minutes </HomeTeamGoaler></Game>
<Game><GameNumber>Pro38</GameNumber><Link>UHA-38.html</Link><VisitorTeam>Washington Capitals</VisitorTeam><VisitorTeamScore>5</VisitorTeamScore><VisitorTeamGoal>Alex Ovechkin(3), Dylan Strome(4), Jakob Chychrun(1,2), Pierre-Luc Dubois(2)</VisitorTeamGoal><VisitorTeamGoaler>Logan Thompson (WSH), 24 saves from 25 shots - (0.960), W, 2-1-0, 60:00 minutes </VisitorTeamGoaler><HomeTeam>New York Rangers</HomeTeam><HomeTeamScore>1</HomeTeamScore><HomeTeamGoal>Adam Fox(3)</HomeTeamGoal><HomeTeamGoaler>Igor Shesterkin (NYR), 31 saves from 36 shots - (0.861), L, 2-2-0, 60:00 minutes </HomeTeamGoaler></Game>
</STHS-TodayGame>
